kucoinfutures/__init__.py
kucoinfutures/ccxt/__init__.py
kucoinfutures/ccxt/kucoinfutures.py
kucoinfutures/ccxt/abstract/kucoinfutures.py
kucoinfutures/ccxt/async_support/__init__.py
kucoinfutures/ccxt/async_support/kucoinfutures.py
kucoinfutures/ccxt/async_support/base/__init__.py
kucoinfutures/ccxt/async_support/base/exchange.py
kucoinfutures/ccxt/async_support/base/throttler.py
kucoinfutures/ccxt/async_support/base/ws/__init__.py
kucoinfutures/ccxt/async_support/base/ws/cache.py
kucoinfutures/ccxt/async_support/base/ws/client.py
kucoinfutures/ccxt/async_support/base/ws/functions.py
kucoinfutures/ccxt/async_support/base/ws/future.py
kucoinfutures/ccxt/async_support/base/ws/order_book.py
kucoinfutures/ccxt/async_support/base/ws/order_book_side.py
kucoinfutures/ccxt/base/__init__.py
kucoinfutures/ccxt/base/decimal_to_precision.py
kucoinfutures/ccxt/base/errors.py
kucoinfutures/ccxt/base/exchange.py
kucoinfutures/ccxt/base/precise.py
kucoinfutures/ccxt/base/types.py
kucoinfutures/ccxt/pro/__init__.py
kucoinfutures/ccxt/pro/kucoinfutures.py
kucoinfutures/ccxt/static_dependencies/README.md
kucoinfutures/ccxt/static_dependencies/__init__.py
kucoinfutures/ccxt/static_dependencies/bip/__init__.py
kucoinfutures/ccxt/static_dependencies/bip/addr/P2PKH_addr.py
kucoinfutures/ccxt/static_dependencies/bip/addr/__init__.py
kucoinfutures/ccxt/static_dependencies/bip/addr/addr_dec_utils.py
kucoinfutures/ccxt/static_dependencies/bip/addr/addr_key_validator.py
kucoinfutures/ccxt/static_dependencies/bip/addr/iaddr_decoder.py
kucoinfutures/ccxt/static_dependencies/bip/addr/iaddr_encoder.py
kucoinfutures/ccxt/static_dependencies/bip/base58/__init__.py
kucoinfutures/ccxt/static_dependencies/bip/base58/base58.py
kucoinfutures/ccxt/static_dependencies/bip/base58/base58_ex.py
kucoinfutures/ccxt/static_dependencies/bip/base58/base58_xmr.py
kucoinfutures/ccxt/static_dependencies/bip/bech32/__init__.py
kucoinfutures/ccxt/static_dependencies/bip/bech32/bch_bech32.py
kucoin_futures_api-0.0.119.dist-info/METADATA
kucoin_futures_api-0.0.119.dist-info/WHEEL
kucoin_futures_api-0.0.119.dist-info/RECORD
